AI4XDE/__init__.py
AI4XDE/algorithm/FBPINN.py
AI4XDE/algorithm/FI_PINN.py
AI4XDE/algorithm/HPO.py
AI4XDE/algorithm/PINN.py
AI4XDE/algorithm/R3Sampling.py
AI4XDE/algorithm/RAD.py
AI4XDE/algorithm/RAR_D.py
AI4XDE/algorithm/RAR_G.py
AI4XDE/algorithm/Random_R.py
AI4XDE/algorithm/TimeMarching.py
AI4XDE/algorithm/Uniform.py
AI4XDE/algorithm/__init__.py
AI4XDE/algorithm/gPINN.py
AI4XDE/cases/ConvectionCases.py
AI4XDE/cases/FuncCases.py
AI4XDE/cases/InverseCases.py
AI4XDE/cases/PDECases.py
AI4XDE/cases/PoissonCases.py
AI4XDE/cases/WaveCases.py
AI4XDE/cases/__init__.py
AI4XDE/data/Allen_Cahn.mat
AI4XDE/data/Burgers.npz
AI4XDE/data/Flow_in_LidDriven_Cavity_u.csv
AI4XDE/data/Flow_in_LidDriven_Cavity_v.csv
AI4XDE/data/Lorenz.npz
AI4XDE/data/NLS.mat
AI4XDE/data/Poisson_Lshape.npz
AI4XDE/data/cylinder_nektar_wake.mat
AI4XDE/data/dataset.test
AI4XDE/data/dataset.train
AI4XDE/data/mf_hi_test.dat
AI4XDE/data/mf_hi_train.dat
AI4XDE/data/mf_lo_train.dat
AI4XDE/data/reaction.npz
AI4XDE/solver/PDESolver.py
AI4XDE/solver/__init__.py
AI4XDE/utils/Math.py
AI4XDE/utils/Visualization.py
AI4XDE/utils/__init__.py
AI4XDE/utils/backend.py
ai4xde-0.4.1.dist-info/LICENSE
ai4xde-0.4.1.dist-info/METADATA
ai4xde-0.4.1.dist-info/WHEEL
ai4xde-0.4.1.dist-info/top_level.txt
ai4xde-0.4.1.dist-info/zip-safe
ai4xde-0.4.1.dist-info/RECORD
