Metadata-Version: 2.1
Name: ai4xde
Version: 0.4.1
Summary: AI4XDE is a library for scientific machine learning and physics-informed learning
Author: xuelanghanbao
Author-email: xuelanghanbao@gmail.com
License: GNU Lesser General Public License v2 (LGPLv2) (LGPL-2.1)
Project-URL: Code, https://gitee.com/xuelanghanbao/AI4XDE
Project-URL: Issue tracker, https://gitee.com/xuelanghanbao/AI4XDE/issues
Classifier: Development Status :: 4 - Beta
Classifier: Intended Audience :: Developers
Classifier: License :: OSI Approved :: GNU Lesser General Public License v2 (LGPLv2)
Classifier: Programming Language :: Python
Classifier: Programming Language :: Python :: 3 :: Only
Classifier: Programming Language :: Python :: 3.7
Classifier: Programming Language :: Python :: 3.8
Classifier: Programming Language :: Python :: 3.9
Classifier: Programming Language :: Python :: 3.10
Classifier: Programming Language :: Python :: 3.11
Classifier: Topic :: Scientific/Engineering
Classifier: Topic :: Scientific/Engineering :: Artificial Intelligence
Classifier: Topic :: Scientific/Engineering :: Mathematics
Requires-Python: >=3.7
License-File: LICENSE
Requires-Dist: deepxde
Requires-Dist: numpy
Requires-Dist: scipy
Requires-Dist: matplotlib
